rtl/cordic_at.v
// cordic_at.v
// Pipelined CORDIC arctangent in vectoring mode. Computes arctan(y_in / x_in)
// using only shifts and adds. Handles all four input quadrants.

// NOTE: since we only need the ratio y/x, we can ignore the growing magnitude,
// the angle comes out correctly regardless.

module cordic_at #(
    parameter W          = 18,  // word width for x/y inputs and angle output
    parameter ITERATIONS = 16   // number of CORDIC iterations (1-16)
                                // --> more iterations = more accurate but higher latency
)(
    input  wire                  clk,
    input  wire                  rst_n,     // active-low asynchronous reset

    input  wire signed [W-1:0]   x_in,     // x component, Q1.(W-2) signed fixed-point
                                           // x^2+y^2 <= 1 required (magnitude grows due to CORDIC gain, prevent overflow)
                                           // we can ignore as stokes inputs s1^2 + s2^2 + s3^2 <= 1
    input  wire signed [W-1:0]   y_in,     // y component, Q1.(W-2) signed fixed-point
    input  wire                  in_valid, // high for one cycle when x_in/y_in are valid

    // arctan(y_in / x_in) in Q2.(W-3) format (scale = 2^(W-3)) 
    // we need 3 int bits to represent range [-pi, pi]
    output wire signed [W-1:0]   angle_out,
    output wire                  out_valid
);
    // returns atan(2^-idx) in Q2.(W-3) format: atan_lut[i] = round(atan(2^-i) * 2^(W-3))
    // precomputed for ITERATIONS=16, W=18 (scale = 2^15 = 32768).
    // regenerate values if ITERATIONS changes; regenerate scale if W changes.
    function signed [W-1:0] atan_lut;
        input integer idx;
        case (idx)
            0:  atan_lut = 18'sd25736;  // atan(2^0)  = pi/4  = 0.7854 rad = 45 deg
            1:  atan_lut = 18'sd15192;  // atan(2^-1) = 0.4636 rad = 26.6 deg
            2:  atan_lut = 18'sd8028;
            3:  atan_lut = 18'sd4075;
            4:  atan_lut = 18'sd2045;   // 'sd: signed, decimal value 2045
            5:  atan_lut = 18'sd1024;
            6:  atan_lut = 18'sd512;
            7:  atan_lut = 18'sd256;
            8:  atan_lut = 18'sd128;
            9:  atan_lut = 18'sd64;
            10: atan_lut = 18'sd32;
            11: atan_lut = 18'sd16;
            12: atan_lut = 18'sd8;
            13: atan_lut = 18'sd4;
            14: atan_lut = 18'sd2;
            15: atan_lut = 18'sd1;
            default: atan_lut = 18'sd0;
        endcase
    endfunction

    // Pipeline registers
    reg signed [W-1:0] x_pipe [0:ITERATIONS];
    reg signed [W-1:0] y_pipe [0:ITERATIONS];
    reg signed [W-1:0] z_pipe [0:ITERATIONS]; // z: angle accumulator
    reg valid_pipe [0:ITERATIONS];

    // register inputs and correct quadrant so x >= 0 before CORDIC iterations
    always @(posedge clk or negedge rst_n) begin
        if (!rst_n) begin
            x_pipe[0]     <= 0;
            y_pipe[0]     <= 0;
            z_pipe[0]     <= 0;
            valid_pipe[0] <= 1'b0;
        end else begin
            valid_pipe[0] <= in_valid;
            if (x_in[W-1]) begin           // x < 0: rotate into right half-plane
                if (!y_in[W-1]) begin      // quadrant 2 (x<0, y>=0): rotate -90 deg, offset z by +pi/2
                    x_pipe[0] <=  y_in;
                    y_pipe[0] <= -x_in;
                    z_pipe[0] <=  18'sd51472;  // pi/2 in Q2.(W-3): round(pi/2 * 2^15)
                end else begin             // quadrant 3 (x<0, y<0): rotate +90 deg, offset z by -pi/2
                    x_pipe[0] <= -y_in;
                    y_pipe[0] <=  x_in;
                    z_pipe[0] <= -18'sd51472;
                end
            end else begin                 // x >= 0: no correction needed
                x_pipe[0] <= x_in;
                y_pipe[0] <= y_in;
                z_pipe[0] <= 0;
            end
        end
    end

    // for each ITERATIONS --> one CORDIC rotation per stage.
    // each stage drives y toward 0 by rotating by atan(2^-i), accumulating the angle in z.
    genvar i;
    generate
        for (i = 0; i < ITERATIONS; i = i + 1) begin : cordic_stage
            always @(posedge clk or negedge rst_n) begin
                if (!rst_n) begin
                    x_pipe[i+1]     <= 0;
                    y_pipe[i+1]     <= 0;
                    z_pipe[i+1]     <= 0;
                    valid_pipe[i+1] <= 1'b0;
                end else begin
                    valid_pipe[i+1] <= valid_pipe[i];
                    if (y_pipe[i][W-1]) begin  // y < 0: rotate counterclockwise
                        x_pipe[i+1] <= x_pipe[i] - ($signed(y_pipe[i]) >>> i); // >>> arithmetic right shift
                        y_pipe[i+1] <= y_pipe[i] + ($signed(x_pipe[i]) >>> i);
                        z_pipe[i+1] <= z_pipe[i] - atan_lut(i);
                    end else begin             // y >= 0: rotate clockwise
                        x_pipe[i+1] <= x_pipe[i] + ($signed(y_pipe[i]) >>> i);
                        y_pipe[i+1] <= y_pipe[i] - ($signed(x_pipe[i]) >>> i);
                        z_pipe[i+1] <= z_pipe[i] + atan_lut(i);
                    end
                end
            end
        end
    endgenerate

    assign angle_out = z_pipe[ITERATIONS];
    assign out_valid  = valid_pipe[ITERATIONS];


endmodule

rtl/sqrt_lut.v
// sqrt_lut.v
// Computes sqrt(1 - s3^2) via lookup table for the arcsin-to-arctan conversion:
// arcsin(S3) = arctan(S3 / sqrt(1 - S3^2)).

module sqrt_lut #(
    parameter W        = 18,             // output word width, Q1.(W-2) format
    parameter LUT_FILE = "rtl/sqrt_lut.hex"  // precomputed by scripts/gen_sqrt_lut.py
)(
    input  wire                clk,
    input  wire                rst_n,    // active-low asynchronous reset

    input  wire signed [W-1:0] s3_in,   // S3 Stokes parameter, Q1.(W-2), range [-1, 1]
    input  wire                in_valid,

    // sqrt(1 - s3_in^2), Q1.(W-2) format, range [0, 1]. Latency: 1 clock cycle.
    output reg  signed [W-1:0] sqrt_out,
    output reg                 out_valid
);

    // 2048-entry ROM: lut[k] = round(sqrt(1 - (k/2048)^2) * 2^(W-2))
    // indexed by |S3| — symmetric around 0 so only the positive half is stored.
    // generated by scripts/gen_sqrt_lut.py.
    reg [W-1:0] lut [0:2047];
    initial $readmemh(LUT_FILE, lut);

    // absolute value of s3_in (two's complement negation)
    wire [W-1:0] s3_abs = s3_in[W-1] ? (~s3_in + 1'b1) : s3_in;

    // convert Q1.(W-2) absolute value to 11-bit LUT index in [0, 2047].
    // s3_abs represents values in [0, 1]; dividing by 2^(W-13) maps to [0, 2048].
    // clamp to 2047 for the edge case s3 = -1.0 exactly (s3_abs = 2^(W-2) = 65536).
    localparam IDX_SHIFT = W - 13;                                     // for W=18: shift by 5
    wire [11:0] lut_idx_raw = s3_abs[W-2:IDX_SHIFT];                  // 12 bits, range [0, 2048]
    wire [10:0] lut_idx     = (lut_idx_raw > 12'd2047) ? 11'd2047 : lut_idx_raw[10:0];

    always @(posedge clk or negedge rst_n) begin
        if (!rst_n) begin
            sqrt_out  <= 0;
            out_valid <= 1'b0;
        end else begin
            out_valid <= in_valid;
            sqrt_out  <= lut[lut_idx];
        end
    end

endmodule

rtl/state_decoder.v
// state_decoder.v
// Converts raw ADC samples into normalized Stokes values 
// (S1, S2, S3) and then computes ψ (orientation), χ
// (ellipticity), δ (residual phase angle) via Eq. 3.

module state_decoder #(
    parameter ADC_W = 12,    // raw ADC word width
    parameter STOKES_W = 18, // internal fixed-point width
    parameter ANGLE_W = 18   // Output angle width
)(
    input wire clk,
    input wire rst_n,

    input  wire [ADC_W-1:0]    s1_raw,    // raw ADC sample (ADC_W-bit signed)
    input  wire [ADC_W-1:0]    s2_raw,
    input  wire [ADC_W-1:0]    s3_raw,
    input  wire                in_valid,  

    output reg  [ANGLE_W-1:0]  psi_out,   // ψ, signed fixed-point
    output reg  [ANGLE_W-1:0]  chi_out,   // χ
    output reg  [ANGLE_W-1:0]  delta_out, // δ
    output reg                 out_valid
);

    // Sign-extend raw Stokes values from 12-bit (scale 2^11) to 18-bit (scale 2^16)
    // (2^16 / 2^11) = 2^5 Left shift by 5

    wire signed [STOKES_W-1:0] s1;
    wire signed [STOKES_W-1:0] s2;
    wire signed [STOKES_W-1:0] s3;

    assign s1 = { {(STOKES_W-ADC_W){s1_raw[ADC_W-1]}},s1_raw } <<< (STOKES_W - ADC_W - 1);
    assign s2 = { {(STOKES_W-ADC_W){s2_raw[ADC_W-1]}},s2_raw } <<< (STOKES_W - ADC_W - 1);
    assign s3 = { {(STOKES_W-ADC_W){s3_raw[ADC_W-1]}},s3_raw } <<< (STOKES_W - ADC_W - 1);
    
    // Instantiate submodules
    // 2ψ = arctan(s2 / s1)
    // 2χ = arcsin(s3) = arctan(s3 / sqrt(1-s3^2))
    // δ = arctan(s3 / s2)

    // chi path as 1 extra cycle (sqrt_lut latency)
    // delay inputs to cordic_psi and cordic_delta to ensure outputs arrive at the same time

    reg signed [STOKES_W-1:0] s1_d;
    reg signed [STOKES_W-1:0] s2_d;
    reg signed [STOKES_W-1:0] s3_d;
    reg                        in_valid_d;

    // delay logic
    always @(posedge clk or negedge rst_n) begin
        if (!rst_n) begin
            s1_d       <= 0;
            s2_d       <= 0;
            s3_d       <= 0;
            in_valid_d <= 0;
        end else begin
            s1_d       <= s1;
            s2_d       <= s2;
            s3_d       <= s3;
            in_valid_d <= in_valid;
        end
    end

    wire signed [STOKES_W-1:0] psi_raw, chi_raw, delta_raw;
    wire                       psi_valid, chi_valid, delta_valid;
    wire signed [STOKES_W-1:0] sqrt_s3;
    wire                       sqrt_valid;

    cordic_at #(.W(STOKES_W)) cordic_psi (
        .clk      (clk),
        .rst_n    (rst_n),
        .x_in     (s1_d),
        .y_in     (s2_d),
        .in_valid (in_valid_d),
        .angle_out(psi_raw),
        .out_valid(psi_valid)
    );

    cordic_at #(.W(STOKES_W)) cordic_delta (
        .clk      (clk),
        .rst_n    (rst_n),
        .x_in     (s2_d),
        .y_in     (s3_d),
        .in_valid (in_valid_d),
        .angle_out(delta_raw),
        .out_valid(delta_valid)
    );

    sqrt_lut #(.W(STOKES_W)) sqrt_inst (
        .clk      (clk),
        .rst_n    (rst_n),
        .s3_in    (s3),
        .in_valid (in_valid),
        .sqrt_out (sqrt_s3),
        .out_valid(sqrt_valid)
    );

    cordic_at #(.W(STOKES_W)) cordic_chi (
        .clk      (clk),
        .rst_n    (rst_n),
        .x_in     (sqrt_s3),
        .y_in     (s3_d),
        .in_valid (sqrt_valid),
        .angle_out(chi_raw),
        .out_valid(chi_valid)
    );

    // 3. Output ψ, χ, δ

    always @(posedge clk or negedge rst_n) begin
        if (!rst_n) begin
            psi_out <= 0;
            chi_out <= 0;
            delta_out <= 0;
            out_valid <= 0;
        end else begin
            psi_out   <= $signed(psi_raw) >>> 1;
            chi_out   <= $signed(chi_raw) >>> 1;
            delta_out <= delta_raw;
            out_valid <= chi_valid; // all 3 valid signals fire same cycle
        end
    end

endmodule

sim/state_decoder_tb.sv
// state_decoder_tb.sv
// Testbench for state_decoder. Feeds raw Stokes values
// into DUT and verifies output angles.

`timescale 1ns/1ps

module state_decoder_tb;

    localparam ADC_W    = 12;
    localparam STOKES_W = 18;
    localparam ANGLE_W  = 18;

    logic clk;
    logic rst_n;

    logic [ADC_W-1:0]   s1_raw;    // raw ADC sample (ADC_W-bit signed)
    logic [ADC_W-1:0]   s2_raw;
    logic [ADC_W-1:0]   s3_raw;
    logic               in_valid;

    logic [ANGLE_W-1:0] psi_out;   // ψ, signed fixed-point
    logic [ANGLE_W-1:0] chi_out;   // χ
    logic [ANGLE_W-1:0] delta_out; // δ
    logic               out_valid;

    // verify output angles are valid on the same clock edge //

    // instantiate DUT
    state_decoder #(
        .ADC_W   (ADC_W),
        .STOKES_W(STOKES_W),
        .ANGLE_W (ANGLE_W)
    ) dut (
        .clk      (clk),
        .rst_n    (rst_n),
        .s1_raw   (s1_raw),
        .s2_raw   (s2_raw),
        .s3_raw   (s3_raw),
        .in_valid (in_valid),
        .psi_out  (psi_out),
        .chi_out  (chi_out),
        .delta_out(delta_out),
        .out_valid(out_valid)
    );

    // clock generation
    initial clk = 0;
    always #5 clk = ~clk; // 10ns period

    // ADC input scale: 12-bit signed, max positive = 2047 ≈ 1.0 normalized
    localparam ADC_MAX        = (1 << (ADC_W-1)) - 1; // 2047
    localparam ONE_OVER_SQRT2 = 1448; // round(2047 / sqrt(2)): equal s1=s2 or s2=s3 on sphere
    localparam ONE_OVER_SQRT3 = 1182; // round(2047 / sqrt(3)): equal s1=s2=s3 on sphere

    localparam ANGLE_SCALE    = 1 << (ANGLE_W-3); // 32768: Q2.15 counts per radian
    localparam TOLERANCE      = 3;                // CORDIC <= 0.5 counts + sqrt_lut < 1 count; 3 gives safe headroom

    // check task: passes if got is within TOLERANCE of expected
    task check;
        input string               name;
        input signed [ANGLE_W-1:0] got;
        input integer              expected;
        if ($signed(got) >= (expected - TOLERANCE) &&
            $signed(got) <= (expected + TOLERANCE))
            $display("PASS %s: got %0d  expected %0d", name, $signed(got), expected);
        else
            $display("FAIL %s: got %0d  expected %0d", name, $signed(got), expected);
    endtask

    // send task: apply one Stokes input vector and wait for result
    task send;
        input signed [ADC_W-1:0] s1v, s2v, s3v;
        @(posedge clk); #1;
        s1_raw = s1v; s2_raw = s2v; s3_raw = s3v; in_valid = 1;
        @(posedge clk); #1;
        in_valid = 0;
        @(posedge out_valid);
    endtask



    // expected angle values: round(angle_rad * 32768), then >>1 for psi/chi outputs
    // arctan(1)   = pi/4  -> 25736 cordic; psi/chi out = 12868
    // arctan(inf) = pi/2  -> 51472 cordic; psi/chi out = 25736
    // arctan(1/sqrt(2)) ~ 0.6155 rad -> 20168 cordic; chi out = 10084
    initial begin
        $dumpfile("sim/state_decoder_tb.vcd");
        $dumpvars(0, state_decoder_tb);
        rst_n = 0; s1_raw = 0; s2_raw = 0; s3_raw = 0; in_valid = 0;
        repeat(4) @(posedge clk);
        rst_n = 1;
        @(posedge clk);

        // Linear horizontal: s1=1, s2=s3=0 -> psi=0, chi=0; delta=arctan(0/0) undefined, not checked
        send(ADC_MAX, 0, 0);
        check("psi  lin-H",   psi_out,    0);
        check("chi  lin-H",   chi_out,    0);

        // Linear 45 deg: s2=1, s1=s3=0 -> psi=pi/4, chi=0, delta=0
        send(0, ADC_MAX, 0);
        check("psi  lin-45",  psi_out,  25736);
        check("chi  lin-45",  chi_out,      0);
        check("delta lin-45", delta_out,    0);

        // Linear diagonal balanced: s1=s2=1/sqrt(2), s3=0 -> psi=pi/4, chi=0, delta=0
        send(ONE_OVER_SQRT2, ONE_OVER_SQRT2, 0);
        check("psi  sqrt2",   psi_out,  12868);
        check("chi  sqrt2",   chi_out,      0);
        check("delta sqrt2",  delta_out,    0);

        // s2=s3=1/sqrt(2), s1=0 -> psi=pi/4, chi=pi/8, delta=pi/4
        send(0, ONE_OVER_SQRT2, ONE_OVER_SQRT2);
        check("psi  s2s3",    psi_out,  25736);
        check("chi  s2s3",    chi_out,  12868);
        check("delta s2s3",   delta_out,25736);

        // Equal Stokes: s1=s2=s3=1/sqrt(3) -> psi=pi/8, chi~0.308rad/2, delta=pi/4
        send(ONE_OVER_SQRT3, ONE_OVER_SQRT3, ONE_OVER_SQRT3);
        check("psi  sqrt3",   psi_out,  12868);
        check("chi  sqrt3",   chi_out,  10080);
        check("delta sqrt3",  delta_out,25736);

        $finish;
    end

endmodule

sim/state_decoder_tb.vcd
$date
	Fri Aug 14 15:35:20 2026
$end
$version
	Icarus Verilog
$end
$timescale
	1ps
$end
$scope module state_decoder_tb $end
$var wire 18 ! psi_out [17:0] $end
$var wire 1 " out_valid $end
$var wire 18 # delta_out [17:0] $end
$var wire 18 $ chi_out [17:0] $end
$var parameter 44 % ADC_MAX $end
$var parameter 32 & ADC_W $end
$var parameter 47 ' ANGLE_SCALE $end
$var parameter 32 ( ANGLE_W $end
$var parameter 32 ) ONE_OVER_SQRT2 $end
$var parameter 32 * ONE_OVER_SQRT3 $end
$var parameter 32 + STOKES_W $end
$var parameter 32 , TOLERANCE $end
$var reg 1 - clk $end
$var reg 1 . in_valid $end
$var reg 1 / rst_n $end
$var reg 12 0 s1_raw [11:0] $end
$var reg 12 1 s2_raw [11:0] $end
$var reg 12 2 s3_raw [11:0] $end
$scope module dut $end
$var wire 1 - clk $end
$var wire 1 . in_valid $end
$var wire 1 / rst_n $end
$var wire 12 3 s1_raw [11:0] $end
$var wire 12 4 s2_raw [11:0] $end
$var wire 12 5 s3_raw [11:0] $end
$var wire 1 6 sqrt_valid $end
$var wire 18 7 sqrt_s3 [17:0] $end
$var wire 18 8 s3 [17:0] $end
$var wire 18 9 s2 [17:0] $end
$var wire 18 : s1 [17:0] $end
$var wire 1 ; psi_valid $end
$var wire 18 < psi_raw [17:0] $end
$var wire 1 = delta_valid $end
$var wire 18 > delta_raw [17:0] $end
$var wire 1 ? chi_valid $end
$var wire 18 @ chi_raw [17:0] $end
$var parameter 32 A ADC_W $end
$var parameter 32 B ANGLE_W $end
$var parameter 32 C STOKES_W $end
$var reg 18 D chi_out [17:0] $end
$var reg 18 E delta_out [17:0] $end
$var reg 1 F in_valid_d $end
$var reg 1 " out_valid $end
$var reg 18 G psi_out [17:0] $end
$var reg 18 H s1_d [17:0] $end
$var reg 18 I s2_d [17:0] $end
$var reg 18 J s3_d [17:0] $end
$scope module cordic_chi $end
$var wire 18 K angle_out [17:0] $end
$var wire 1 - clk $end
$var wire 1 ? out_valid $end
$var wire 1 / rst_n $end
$var wire 18 L y_in [17:0] $end
$var wire 18 M x_in [17:0] $end
$var wire 1 6 in_valid $end
$var parameter 32 N ITERATIONS $end
$var parameter 32 O W $end
$scope function atan_lut $end
$var integer 32 P idx [31:0] $end
$upscope $end
$scope begin cordic_stage[0] $end
$var parameter 2 Q i $end
$upscope $end
$scope begin cordic_stage[1] $end
$var parameter 2 R i $end
$upscope $end
$scope begin cordic_stage[2] $end
$var parameter 3 S i $end
$upscope $end
$scope begin cordic_stage[3] $end
$var parameter 3 T i $end
$upscope $end
$scope begin cordic_stage[4] $end
$var parameter 4 U i $end
$upscope $end
$scope begin cordic_stage[5] $end
$var parameter 4 V i $end
$upscope $end
$scope begin cordic_stage[6] $end
$var parameter 4 W i $end
$upscope $end
$scope begin cordic_stage[7] $end
$var parameter 4 X i $end
$upscope $end
$scope begin cordic_stage[8] $end
$var parameter 5 Y i $end
$upscope $end
$scope begin cordic_stage[9] $end
$var parameter 5 Z i $end
$upscope $end
$scope begin cordic_stage[10] $end
$var parameter 5 [ i $end
$upscope $end
$scope begin cordic_stage[11] $end
$var parameter 5 \ i $end
$upscope $end
$scope begin cordic_stage[12] $end
$var parameter 5 ] i $end
$upscope $end
$scope begin cordic_stage[13] $end
$var parameter 5 ^ i $end
$upscope $end
$scope begin cordic_stage[14] $end
$var parameter 5 _ i $end
$upscope $end
$scope begin cordic_stage[15] $end
$var parameter 5 ` i $end
$upscope $end
$upscope $end
$scope module cordic_delta $end
$var wire 18 a angle_out [17:0] $end
$var wire 1 - clk $end
$var wire 1 F in_valid $end
$var wire 1 = out_valid $end
$var wire 1 / rst_n $end
$var wire 18 b x_in [17:0] $end
$var wire 18 c y_in [17:0] $end
$var parameter 32 d ITERATIONS $end
$var parameter 32 e W $end
$scope function atan_lut $end
$var integer 32 f idx [31:0] $end
$upscope $end
$scope begin cordic_stage[0] $end
$var parameter 2 g i $end
$upscope $end
$scope begin cordic_stage[1] $end
$var parameter 2 h i $end
$upscope $end
$scope begin cordic_stage[2] $end
$var parameter 3 i i $end
$upscope $end
$scope begin cordic_stage[3] $end
$var parameter 3 j i $end
$upscope $end
$scope begin cordic_stage[4] $end
$var parameter 4 k i $end
$upscope $end
$scope begin cordic_stage[5] $end
$var parameter 4 l i $end
$upscope $end
$scope begin cordic_stage[6] $end
$var parameter 4 m i $end
$upscope $end
$scope begin cordic_stage[7] $end
$var parameter 4 n i $end
$upscope $end
$scope begin cordic_stage[8] $end
$var parameter 5 o i $end
$upscope $end
$scope begin cordic_stage[9] $end
$var parameter 5 p i $end
$upscope $end
$scope begin cordic_stage[10] $end
$var parameter 5 q i $end
$upscope $end
$scope begin cordic_stage[11] $end
$var parameter 5 r i $end
$upscope $end
$scope begin cordic_stage[12] $end
$var parameter 5 s i $end
$upscope $end
$scope begin cordic_stage[13] $end
$var parameter 5 t i $end
$upscope $end
$scope begin cordic_stage[14] $end
$var parameter 5 u i $end
$upscope $end
$scope begin cordic_stage[15] $end
$var parameter 5 v i $end
$upscope $end
$upscope $end
$scope module cordic_psi $end
$var wire 18 w angle_out [17:0] $end
$var wire 1 - clk $end
$var wire 1 F in_valid $end
$var wire 1 ; out_valid $end
$var wire 1 / rst_n $end
$var wire 18 x x_in [17:0] $end
$var wire 18 y y_in [17:0] $end
$var parameter 32 z ITERATIONS $end
$var parameter 32 { W $end
$scope function atan_lut $end
$var integer 32 | idx [31:0] $end
$upscope $end
$scope begin cordic_stage[0] $end
$var parameter 2 } i $end
$upscope $end
$scope begin cordic_stage[1] $end
$var parameter 2 ~ i $end
$upscope $end
$scope begin cordic_stage[2] $end
$var parameter 3 !" i $end
$upscope $end
$scope begin cordic_stage[3] $end
$var parameter 3 "" i $end
$upscope $end
$scope begin cordic_stage[4] $end
$var parameter 4 #" i $end
$upscope $end
$scope begin cordic_stage[5] $end
$var parameter 4 $" i $end
$upscope $end
$scope begin cordic_stage[6] $end
$var parameter 4 %" i $end
$upscope $end
$scope begin cordic_stage[7] $end
$var parameter 4 &" i $end
$upscope $end
$scope begin cordic_stage[8] $end
$var parameter 5 '" i $end
$upscope $end
$scope begin cordic_stage[9] $end
$var parameter 5 (" i $end
$upscope $end
$scope begin cordic_stage[10] $end
$var parameter 5 )" i $end
$upscope $end
$scope begin cordic_stage[11] $end
$var parameter 5 *" i $end
$upscope $end
$scope begin cordic_stage[12] $end
$var parameter 5 +" i $end
$upscope $end
$scope begin cordic_stage[13] $end
$var parameter 5 ," i $end
$upscope $end
$scope begin cordic_stage[14] $end
$var parameter 5 -" i $end
$upscope $end
$scope begin cordic_stage[15] $end
$var parameter 5 ." i $end
$upscope $end
$upscope $end
$scope module sqrt_inst $end
$var wire 1 - clk $end
$var wire 1 . in_valid $end
$var wire 1 / rst_n $end
$var wire 18 /" s3_in [17:0] $end
$var wire 18 0" s3_abs [17:0] $end
$var wire 12 1" lut_idx_raw [11:0] $end
$var wire 11 2" lut_idx [10:0] $end
$var parameter 33 3" IDX_SHIFT $end
$var parameter 128 4" LUT_FILE $end
$var parameter 32 5" W $end
$var reg 1 6 out_valid $end
$var reg 18 6" sqrt_out [17:0] $end
$upscope $end
$upscope $end
$scope task check $end
$var reg 18 7" got [17:0] $end
$var integer 32 8" expected [31:0] $end
$upscope $end
$scope task send $end
$var reg 12 9" s1v [11:0] $end
$var reg 12 :" s2v [11:0] $end
$var reg 12 ;" s3v [11:0] $end
$upscope $end
$upscope $end
$enddefinitions $end
$comment Show the parameter values. $end
$dumpall
b10010 5"
b1110010011101000110110000101111011100110111000101110010011101000101111101101100011101010111010000101110011010000110010101111000 4"
b101 3"
b1111 ."
b1110 -"
b1101 ,"
b1100 +"
b1011 *"
b1010 )"
b1001 ("
b1000 '"
b111 &"
b110 %"
b101 $"
b100 #"
b11 ""
b10 !"
b1 ~
b0 }
b10010 {
b10000 z
b1111 v
b1110 u
b1101 t
b1100 s
b1011 r
b1010 q
b1001 p
b1000 o
b111 n
b110 m
b101 l
b100 k
b11 j
b10 i
b1 h
b0 g
b10010 e
b10000 d
b1111 `
b1110 _
b1101 ^
b1100 ]
b1011 \
b1010 [
b1001 Z
b1000 Y
b111 X
b110 W
b101 V
b100 U
b11 T
b10 S
b1 R
b0 Q
b10010 O
b10000 N
b10010 C
b10010 B
b1100 A
b11 ,
b10010 +
b10010011110 *
b10110101000 )
b10010 (
b1000000000000000 '
b1100 &
b11111111111 %
$end
#0
$dumpvars
bx ;"
bx :"
bx 9"
bx 8"
bx 7"
b0 6"
b0 2"
b0 1"
b0 0"
b0 /"
bx |
b0 y
b0 x
b0 w
bx f
b0 c
b0 b
b0 a
bx P
b0 M
b0 L
b0 K
b0 J
b0 I
b0 H
b0 G
0F
b0 E
b0 D
b0 @
0?
b0 >
0=
b0 <
0;
b0 :
b0 9
b0 8
b0 7
06
b0 5
b0 4
b0 3
b0 2
b0 1
b0 0
0/
0.
0-
b0 $
b0 #
0"
b0 !
$end
#5000
1-
#10000
0-
#15000
1-
#20000
0-
#25000
1-
#30000
0-
#35000
b1 <
b1 w
b1 >
b1 a
b10000000000000000 7
b10000000000000000 M
b10000000000000000 6"
b1 @
b1 K
b0 |
b0 f
b0 P
1/
1-
#40000
0-
#45000
b1 #
b1 E
b11 @
b11 K
b11 >
b11 a
b11 <
b11 w
b1111 P
b1111 f
b1111 |
b0 ;"
b0 :"
b11111111111 9"
1-
#50000
0-
#55000
b111 <
b111 w
b111 >
b111 a
b111 @
b111 K
b11 #
b11 E
b1 $
b1 D
b1 !
b1 G
b0 |
b0 f
b0 P
1-
#56000
b1111111111100000 :
1.
b11111111111 0
b11111111111 3
#60000
0-
#65000
b111 #
b111 E
b11 $
b11 D
b11 !
b11 G
1F
b1111111111100000 H
b1111111111100000 x
b1111 @
b1111 K
16
b1111 >
b1111 a
b1111 <
b1111 w
b1111 P
b1111 f
b1111 |
1-
#66000
0.
#70000
0-
#75000
b11111 <
b11111 w
b11111 >
b11111 a
06
b11111 @
b11111 K
0F
b1111 #
b1111 E
b111 $
b111 D
b111 !
b111 G
b0 |
b0 f
b0 P
1-
#80000
0-
#85000
b11111 #
b11111 E
b1111 $
b1111 D
b1111 !
b1111 G
b111111 @
b111111 K
b111111 >
b111111 a
b111111 <
b111111 w
b1111 P
b1111 f
b1111 |
1-
#90000
0-
#95000
b1111111 <
b1111111 w
b1111111 >
b1111111 a
b1111111 @
b1111111 K
b111111 #
b111111 E
b11111 $
b11111 D
b11111 !
b11111 G
b0 |
b0 f
b0 P
1-
#100000
0-
#105000
b1111111 #
b1111111 E
b111111 $
b111111 D
b111111 !
b111111 G
b11111111 @
b11111111 K
b11111111 >
b11111111 a
b11111111 <
b11111111 w
b1111 P
b1111 f
b1111 |
1-
#110000
0-
#115000
b111111111 <
b111111111 w
b111111111 >
b111111111 a
b111111111 @
b111111111 K
b11111111 #
b11111111 E
b1111111 $
b1111111 D
b1111111 !
b1111111 G
b0 |
b0 f
b0 P
1-
#120000
0-
#125000
b111111111 #
b111111111 E
b11111111 $
b11111111 D
b11111111 !
b11111111 G
b1111111111 @
b1111111111 K
b1111111111 >
b1111111111 a
b1111111111 <
b1111111111 w
b1111 P
b1111 f
b1111 |
1-
#130000
0-
#135000
b11111111111 <
b11111111111 w
b11111111111 >
b11111111111 a
b11111111111 @
b11111111111 K
b1111111111 #
b1111111111 E
b111111111 $
b111111111 D
b111111111 !
b111111111 G
b0 |
b0 f
b0 P
1-
#140000
0-
#145000
b11111111111 #
b11111111111 E
b1111111111 $
b1111111111 D
b1111111111 !
b1111111111 G
b111111111100 @
b111111111100 K
b111111111100 >
b111111111100 a
b111111111100 <
b111111111100 w
b1111 P
b1111 f
b1111 |
1-
#150000
0-
#155000
b1111111100111 <
b1111111100111 w
b1111111100111 >
b1111111100111 a
b1111111100111 @
b1111111100111 K
b111111111100 #
b111111111100 E
b11111111110 $
b11111111110 D
b11111111110 !
b11111111110 G
b0 |
b0 f
b0 P
1-
#160000
0-
#165000
b1111111100111 #
b1111111100111 E
b111111110011 $
b111111110011 D
b111111110011 !
b111111110011 G
b11111101000011 @
b11111101000011 K
b11111101000011 >
b11111101000011 a
b11111101000011 <
b11111101000011 w
b1111 P
b1111 f
b1111 |
1-
#170000
0-
#175000
b111101010011011 <
b111101010011011 w
b111101010011011 >
b111101010011011 a
b111101010011011 @
b111101010011011 K
b11111101000011 #
b11111101000011 E
b1111110100001 $
b1111110100001 D
b1111110100001 !
b1111110100001 G
b0 |
b0 f
b0 P
1-
#180000
0-
#185000
b111101010011011 #
b111101010011011 E
b11110101001101 $
b11110101001101 D
b11110101001101 !
b11110101001101 G
b1101111100100011 @
b1101111100100011 K
b1101111100100011 >
b1101111100100011 a
b1101111100100011 <
b1101111100100011 w
b1111 P
b1111 f
b1111 |
1-
#190000
0-
#195000
b1101111100100011 #
b1101111100100011 E
b110111110010001 $
b110111110010001 D
b110111110010001 !
b110111110010001 G
b0 |
b0 f
b0 P
1-
#200000
0-
#205000
b111111111111111111 @
b111111111111111111 K
b1111 P
b1111 f
b1111 |
1-
#210000
0-
#215000
b111111111111111111 $
b111111111111111111 D
b0 |
b0 f
b0 P
1-
#220000
0-
#225000
b1111 P
b1111 f
b1111 |
1-
#230000
0-
#235000
b111111111111111111 <
b111111111111111111 w
1;
1=
1?
b0 |
b0 f
b0 P
1-
#240000
0-
#245000
b11111111111 :"
b0 9"
b0 8"
b111111111111111111 7"
1"
b111111111111111111 !
b111111111111111111 G
0?
0=
0;
b1111 P
b1111 f
b1111 |
1-
#250000
0-
#255000
0"
b0 |
b0 f
b0 P
1-
#256000
b1111111111100000 9
b0 :
1.
b11111111111 1
b11111111111 4
b0 0
b0 3
#260000
0-
#265000
1F
b1111111111100000 I
b1111111111100000 b
b1111111111100000 y
b0 H
b0 x
16
b1111 P
b1111 f
b1111 |
1-
#266000
0.
#270000
0-
#275000
06
0F
b0 |
b0 f
b0 P
1-
#280000
0-
#285000
b1111 P
b1111 f
b1111 |
1-
#290000
0-
#295000
b0 |
b0 f
b0 P
1-
#300000
0-
#305000
b1111 P
b1111 f
b1111 |
1-
#310000
0-
#315000
b0 |
b0 f
b0 P
1-
#320000
0-
#325000
b1111 P
b1111 f
b1111 |
1-
#330000
0-
#335000
b0 |
b0 f
b0 P
1-
#340000
0-
#345000
b1111 P
b1111 f
b1111 |
1-
#350000
0-
#355000
b0 |
b0 f
b0 P
1-
#360000
0-
#365000
b1111 P
b1111 f
b1111 |
1-
#370000
0-
#375000
b0 |
b0 f
b0 P
1-
#380000
0-
#385000
b1111 P
b1111 f
b1111 |
1-
#390000
0-
#395000
b0 |
b0 f
b0 P
1-
#400000
0-
#405000
b1111 P
b1111 f
b1111 |
1-
#410000
0-
#415000
b0 |
b0 f
b0 P
1-
#420000
0-
#425000
b1111 P
b1111 f
b1111 |
1-
#430000
0-
