rtl/threshold_checker.v
// threshold_checker.v
// Compares the decoded V and D reference states against
// tolerance thresholds; asserts beyond_threshold to trigger
// a correction cycle or within_threshold to loop back for
// the next measurement.
//
// BACKGROUND (Sec. 3A of Gül et al.):
//   The fiber transforms known input states S_V and S_D into
//   measured output states S''_V and S''_D. If the measured
//   states match the ideal states within tolerance, the channel
//   is sufficiently compensated and no correction is needed.
//   If any angle has drifted beyond tolerance, a correction
//   cycle is triggered.
//
// IDEAL REFERENCE ANGLES (fixed by choice of V and D states):
//   V (vertical polarization):  psi = pi/2, chi = 0
//   D (diagonal polarization):  psi = pi/4, chi = 0
//
//   In Q2.15 fixed-point (32768 counts = 1 rad):
//     PSI_V_IDEAL  = round(pi/2 * 32768) = 51472
//     PSI_D_IDEAL  = round(pi/4 * 32768) = 25736
//     CHI_IDEAL    = 0  (both V and D are linear, so chi=0)
//
// NOTE: delta is NOT checked here. It is undefined for V
//   (S2=S3=0 makes arctan(S3/S2) degenerate) and feeds
//   directly into the correction_solver algorithm instead.
//
// THRESHOLD:
//   Paper target is 10 degrees on the Poincare sphere.
//   10 deg × (pi/180) × 32768 ≈ 5726 counts.
//   Exposed as a parameter so it can be tuned at synthesis time.

module threshold_checker #(
    parameter ANGLE_W     = 18,
    parameter PSI_V_IDEAL = 18'sd51472,  // pi/2 in Q2.15: ideal psi for V pass
    parameter PSI_D_IDEAL = 18'sd25736,  // pi/4 in Q2.15: ideal psi for D pass
    parameter CHI_IDEAL   = 18'sd0,      // both V and D are linear so chi=0
    parameter THRESHOLD   = 18'sd5726    // 10 deg in Q2.15
)(
    input wire clk,
    input wire rst_n,
    input wire signed [ANGLE_W-1:0] psi,
    input wire signed [ANGLE_W-1:0] chi,
    input wire pass_sel, // 1 = V pass, 0 = D pass
    input wire valid, // high when psi and chi are valid

    output reg correction_needed // 1 = beyond threshold, 0 = within
);
    reg signed [ANGLE_W-1:0] V_psi;
    reg signed [ANGLE_W-1:0] V_chi;

    always @(posedge clk or negedge rst_n) begin
        if (!rst_n) begin
            correction_needed <= 0;
            V_psi             <= 0;
            V_chi             <= 0;
        end else if (valid && pass_sel) begin  // V pass arrived: latch
            V_psi <= $signed(psi);
            V_chi <= $signed(chi);
        end else if (valid && !pass_sel) begin // D pass arrived: compare all four
            correction_needed <= ($signed(V_psi) > $signed(PSI_V_IDEAL) + THRESHOLD) ||
                                 ($signed(V_psi) < $signed(PSI_V_IDEAL) - THRESHOLD) ||
                                 ($signed(V_chi) > $signed(CHI_IDEAL)   + THRESHOLD) ||
                                 ($signed(V_chi) < $signed(CHI_IDEAL)   - THRESHOLD) ||
                                 ($signed(psi)   > $signed(PSI_D_IDEAL) + THRESHOLD) ||
                                 ($signed(psi)   < $signed(PSI_D_IDEAL) - THRESHOLD) ||
                                 ($signed(chi)   > $signed(CHI_IDEAL)   + THRESHOLD) ||
                                 ($signed(chi)   < $signed(CHI_IDEAL)   - THRESHOLD);
        end
    end

endmodule

sim/threshold_checker_tb.sv
// threshold_checker_tb.sv
// Testbench for threshold_checker. Sends V and D pass results and
// verifies correction_needed is asserted correctly.

`timescale 1ns/1ps

module threshold_checker_tb;

    localparam ANGLE_W     = 18;
    localparam PSI_V_IDEAL = 18'sd51472;
    localparam PSI_D_IDEAL = 18'sd25736;
    localparam CHI_IDEAL   = 18'sd0;
    localparam THRESHOLD   = 18'sd5726;    // 10 deg in Q2.15
    localparam TOLERANCE   = 0;            // output is a single bit, exact match only

    logic                      clk;
    logic                      rst_n;
    logic signed [ANGLE_W-1:0] psi;
    logic signed [ANGLE_W-1:0] chi;
    logic                      pass_sel;
    logic                      valid;
    logic                      correction_needed;

    threshold_checker #(
        .ANGLE_W    (ANGLE_W),
        .PSI_V_IDEAL(PSI_V_IDEAL),
        .PSI_D_IDEAL(PSI_D_IDEAL),
        .CHI_IDEAL  (CHI_IDEAL),
        .THRESHOLD  (THRESHOLD)
    ) dut (
        .clk              (clk),
        .rst_n            (rst_n),
        .psi              (psi),
        .chi              (chi),
        .pass_sel         (pass_sel),
        .valid            (valid),
        .correction_needed(correction_needed)
    );

    initial clk = 0;
    always #5 clk = ~clk;

    // check task: verify correction_needed matches expected one cycle after D pass
    task check;
        input string name;
        input        expected;
        @(posedge clk); #1;
        if (correction_needed === expected)
            $display("PASS %s: correction_needed=%0b", name, correction_needed);
        else
            $display("FAIL %s: got=%0b  expected=%0b", name, correction_needed, expected);
    endtask

    // send task: drive one V pass then one D pass, then check result
    task send;
        input signed [ANGLE_W-1:0] psi_v, chi_v;  // V pass angles
        input signed [ANGLE_W-1:0] psi_d, chi_d;  // D pass angles
        // V pass
        @(posedge clk); #1;
        psi = psi_v; chi = chi_v; pass_sel = 1; valid = 1;
        @(posedge clk); #1;
        valid = 0;
        // D pass
        @(posedge clk); #1;
        psi = psi_d; chi = chi_d; pass_sel = 0; valid = 1;
        @(posedge clk); #1;
        valid = 0;
    endtask

    initial begin
        $dumpfile("sim/threshold_checker_tb.vcd");
        $dumpvars(0, threshold_checker_tb);

        rst_n = 0; psi = 0; chi = 0; pass_sel = 0; valid = 0;
        repeat(4) @(posedge clk);
        rst_n = 1;
        @(posedge clk);

        // both V and D ideal: no correction needed
        send(PSI_V_IDEAL, CHI_IDEAL, PSI_D_IDEAL, CHI_IDEAL);
        check("ideal V and D", 0);

        // V psi just inside upper threshold boundary: no correction
        send(PSI_V_IDEAL + THRESHOLD, CHI_IDEAL, PSI_D_IDEAL, CHI_IDEAL);
        check("V psi at upper boundary", 0);

        // V psi just over upper threshold: correction needed
        send(PSI_V_IDEAL + THRESHOLD + 1, CHI_IDEAL, PSI_D_IDEAL, CHI_IDEAL);
        check("V psi over upper boundary", 1);

        // V psi just inside lower threshold boundary: no correction
        send(PSI_V_IDEAL - THRESHOLD, CHI_IDEAL, PSI_D_IDEAL, CHI_IDEAL);
        check("V psi at lower boundary", 0);

        // V psi just under lower threshold: correction needed
        send(PSI_V_IDEAL - THRESHOLD - 1, CHI_IDEAL, PSI_D_IDEAL, CHI_IDEAL);
        check("V psi under lower boundary", 1);

        // D psi over threshold: correction needed
        send(PSI_V_IDEAL, CHI_IDEAL, PSI_D_IDEAL + THRESHOLD + 1, CHI_IDEAL);
        check("D psi over threshold", 1);

        // V chi over threshold: correction needed
        send(PSI_V_IDEAL, THRESHOLD + 1, PSI_D_IDEAL, CHI_IDEAL);
        check("V chi over threshold", 1);

        // D chi under threshold (negative): correction needed
        send(PSI_V_IDEAL, CHI_IDEAL, PSI_D_IDEAL, -(THRESHOLD + 1));
        check("D chi under threshold", 1);

        // both V and D at maximum drift (worst case): correction needed
        send(PSI_V_IDEAL + THRESHOLD + 1, THRESHOLD + 1,
             PSI_D_IDEAL + THRESHOLD + 1, THRESHOLD + 1);
        check("all angles over threshold", 1);

        $finish;
    end

endmodule

sim/threshold_checker_tb.vcd
$date
	Fri Aug 14 23:54:33 2026
$end
$version
	Icarus Verilog
$end
$timescale
	1ps
$end
$scope module threshold_checker_tb $end
$var wire 1 ! correction_needed $end
$var parameter 32 " ANGLE_W $end
$var parameter 18 # CHI_IDEAL $end
$var parameter 18 $ PSI_D_IDEAL $end
$var parameter 18 % PSI_V_IDEAL $end
$var parameter 18 & THRESHOLD $end
$var parameter 32 ' TOLERANCE $end
$var reg 18 ( chi [17:0] $end
$var reg 1 ) clk $end
$var reg 1 * pass_sel $end
$var reg 18 + psi [17:0] $end
$var reg 1 , rst_n $end
$var reg 1 - valid $end
$scope module dut $end
$var wire 18 . chi [17:0] $end
$var wire 1 ) clk $end
$var wire 1 * pass_sel $end
$var wire 18 / psi [17:0] $end
$var wire 1 , rst_n $end
$var wire 1 - valid $end
$var parameter 32 0 ANGLE_W $end
$var parameter 18 1 CHI_IDEAL $end
$var parameter 18 2 PSI_D_IDEAL $end
$var parameter 18 3 PSI_V_IDEAL $end
$var parameter 18 4 THRESHOLD $end
$var reg 18 5 V_chi [17:0] $end
$var reg 18 6 V_psi [17:0] $end
$var reg 1 ! correction_needed $end
$upscope $end
$scope task check $end
$var reg 1 7 expected $end
$upscope $end
$scope task send $end
$var reg 18 8 chi_d [17:0] $end
$var reg 18 9 chi_v [17:0] $end
$var reg 18 : psi_d [17:0] $end
$var reg 18 ; psi_v [17:0] $end
$upscope $end
$upscope $end
$enddefinitions $end
$comment Show the parameter values. $end
$dumpall
b1011001011110 4
b1100100100010000 3
b110010010001000 2
b0 1
b10010 0
b0 '
b1011001011110 &
b1100100100010000 %
b110010010001000 $
b0 #
b10010 "
$end
#0
$dumpvars
bx ;
bx :
bx 9
bx 8
x7
b0 6
b0 5
b0 /
b0 .
0-
0,
b0 +
0*
0)
b0 (
0!
$end
#5000
1)
#10000
0)
#15000
1)
#20000
0)
#25000
1)
#30000
0)
#35000
1,
1)
#40000
0)
#45000
b0 8
b110010010001000 :
b0 9
b1100100100010000 ;
1)
#50000
0)
#55000
1)
#56000
1-
1*
b1100100100010000 +
b1100100100010000 /
#60000
0)
#65000
b1100100100010000 6
1)
#66000
0-
#70000
0)
#75000
1)
#76000
1-
0*
b110010010001000 +
b110010010001000 /
#80000
0)
#85000
1)
#86000
07
0-
#90000
0)
#95000
1)
#96000
b1101111101101110 ;
#100000
0)
#105000
1)
#106000
1-
1*
b1101111101101110 +
b1101111101101110 /
#110000
0)
#115000
b1101111101101110 6
1)
#116000
0-
#120000
0)
#125000
1)
#126000
1-
0*
b110010010001000 +
b110010010001000 /
#130000
0)
#135000
1)
#136000
0-
#140000
0)
#145000
1)
#146000
b1101111101101111 ;
#150000
0)
#155000
1)
#156000
1-
1*
b1101111101101111 +
b1101111101101111 /
#160000
0)
#165000
b1101111101101111 6
1)
#166000
0-
#170000
0)
#175000
1)
#176000
1-
0*
b110010010001000 +
b110010010001000 /
#180000
0)
#185000
1!
1)
#186000
17
0-
#190000
0)
#195000
1)
#196000
b1011001010110010 ;
#200000
0)
#205000
1)
#206000
1-
1*
b1011001010110010 +
b1011001010110010 /
#210000
0)
#215000
b1011001010110010 6
1)
#216000
0-
#220000
0)
#225000
1)
#226000
1-
0*
b110010010001000 +
b110010010001000 /
#230000
0)
#235000
0!
1)
#236000
07
0-
#240000
0)
#245000
1)
#246000
b1011001010110001 ;
#250000
0)
#255000
1)
#256000
1-
1*
b1011001010110001 +
b1011001010110001 /
#260000
0)
#265000
b1011001010110001 6
1)
#266000
0-
#270000
0)
#275000
1)
#276000
1-
0*
b110010010001000 +
b110010010001000 /
#280000
0)
#285000
1!
1)
#286000
17
0-
#290000
0)
#295000
1)
#296000
b111101011100111 :
b1100100100010000 ;
#300000
0)
#305000
1)
#306000
1-
1*
b1100100100010000 +
b1100100100010000 /
#310000
0)
#315000
b1100100100010000 6
1)
#316000
0-
#320000
0)
#325000
1)
#326000
1-
0*
b111101011100111 +
b111101011100111 /
#330000
0)
#335000
1)
#336000
0-
#340000
0)
#345000
1)
#346000
b110010010001000 :
b1011001011111 9
#350000
0)
#355000
1)
#356000
1-
1*
b1011001011111 (
b1011001011111 .
b1100100100010000 +
b1100100100010000 /
#360000
0)
#365000
b1011001011111 5
1)
#366000
0-
#370000
0)
#375000
1)
#376000
1-
0*
b0 (
b0 .
b110010010001000 +
b110010010001000 /
#380000
0)
#385000
1)
#386000
0-
#390000
0)
#395000
1)
#396000
b111110100110100001 8
b0 9
#400000
0)
#405000
1)
#406000
1-
1*
b1100100100010000 +
b1100100100010000 /
#410000
0)
#415000
b0 5
1)
#416000
0-
#420000
0)
#425000
1)
#426000
1-
0*
b111110100110100001 (
b111110100110100001 .
b110010010001000 +
b110010010001000 /
#430000
0)
#435000
1)
#436000
0-
#440000
0)
#445000
1)
#446000
b1011001011111 8
b111101011100111 :
b1011001011111 9
b1101111101101111 ;
#450000
0)
#455000
1)
#456000
1-
1*
b1011001011111 (
b1011001011111 .
b1101111101101111 +
b1101111101101111 /
#460000
0)
#465000
b1011001011111 5
b1101111101101111 6
1)
#466000
0-
#470000
0)
#475000
1)
#476000
1-
0*
b111101011100111 +
b111101011100111 /
#480000
0)
#485000
1)
#486000
0-
